<?xml version="1.0" encoding="UTF-8"?>
<!--
Copyright (c) 2016 NumberFour AG.
All rights reserved. This program and the accompanying materials
are made available under the terms of the Eclipse Public License v1.0
which accompanies this distribution, and is available at
http://www.eclipse.org/legal/epl-v10.html

Contributors:
  NumberFour AG - Initial API and implementation
-->
<feature
      id="org.eclipse.n4js.dependencies.sdk"
      label="N4JS IDE Core Dependencies SDK"
      version="0.0.1.qualifier"
      provider-name="%providerName"
      license-feature="org.eclipse.license"
      license-feature-version="1.0.1.v20140414-1359">

   <description>
      [Enter Feature Description here.]
   </description>

   <copyright>
      Copyright (c) 2016 NumberFour AG.
All rights reserved. This program and the accompanying materials
are made available under the terms of the Eclipse Public License v1.0
which accompanies this distribution, and is available at
http://www.eclipse.org/legal/epl-v10.html

Contributors:
  NumberFour AG - Initial API and implementation
   </copyright>

   <license url="%licenseURL">
      %license
   </license>

   <requires>
      <import plugin="org.eclipse.core.resources"/>
      <import plugin="org.eclipse.core.runtime"/>
      <import plugin="org.eclipse.jdt.core"/>
      <import plugin="org.apache.log4j"/>
      <import plugin="com.google.guava"/>
      <import plugin="org.eclipse.emf.ecore"/>
      <import plugin="com.google.inject"/>
      <import plugin="org.eclipse.xtext.util"/>
      <import plugin="org.antlr.runtime"/>
      <import plugin="org.eclipse.emf.common"/>
      <import plugin="org.eclipse.text"/>
      <import plugin="org.eclipse.xtend.lib"/>
      <import plugin="org.eclipse.xtend.lib.macro"/>
      <import plugin="org.eclipse.xtext.xbase.lib"/>
      <import plugin="org.eclipse.core.commands"/>
      <import plugin="org.eclipse.debug.core"/>
      <import plugin="org.eclipse.xtext"/>
      <import plugin="org.eclipse.equinox.common"/>
      <import plugin="org.eclipse.emf.ecore.xmi"/>
      <import plugin="org.eclipse.osgi"/>
      <import plugin="com.ibm.icu"/>
      <import plugin="org.objectweb.asm"/>
      <import plugin="org.eclipse.xtext.ecore"/>
      <import plugin="org.junit"/>
      <import plugin="org.eclipse.core.expressions"/>
      <import plugin="org.eclipse.core.filesystem"/>
      <import plugin="org.eclipse.core.variables"/>
      <import plugin="org.eclipse.core.jobs"/>
      <import plugin="org.eclipse.core.contenttype"/>
      <import plugin="org.eclipse.equinox.app"/>
      <import plugin="org.eclipse.equinox.preferences"/>
      <import plugin="org.eclipse.equinox.registry"/>
      <import plugin="org.hamcrest.core"/>
      <import plugin="org.eclipse.xtext.common.types"/>
      <import plugin="org.eclipse.emf.ecore.xcore"/>
      <import plugin="org.eclipse.emf.ecore.xcore.lib"/>
      <import plugin="org.eclipse.emf.codegen.ecore.xtext"/>
      <import plugin="org.eclipse.emf.mwe2.runtime"/>
      <import plugin="javax.xml"/>
      <import plugin="org.eclipse.emf.codegen.ecore"/>
      <import plugin="org.eclipse.emf.codegen"/>
      <import plugin="org.eclipse.jdt.launching"/>
      <import plugin="org.eclipse.jdt.debug"/>
      <import plugin="org.apache.commons.logging"/>
      <import plugin="org.eclipse.xtext.xbase"/>
      <import plugin="org.eclipse.core.databinding"/>
      <import plugin="org.eclipse.core.databinding.property"/>
      <import plugin="org.eclipse.core.databinding.observable"/>
      <import plugin="org.eclipse.help"/>
      <import plugin="org.eclipse.equinox.p2.engine"/>
      <import plugin="org.eclipse.equinox.p2.metadata"/>
      <import plugin="org.eclipse.equinox.bidi"/>
      <import plugin="org.eclipse.core.filebuffers"/>
      <import plugin="org.eclipse.compare.core"/>
      <import plugin="org.eclipse.equinox.p2.core"/>
      <import plugin="org.eclipse.equinox.p2.repository"/>
      <import plugin="org.eclipse.equinox.security"/>
      <import plugin="org.eclipse.e4.core.contexts"/>
      <import plugin="org.eclipse.e4.core.di"/>
      <import plugin="org.eclipse.e4.core.services"/>
      <import plugin="org.eclipse.e4.core.commands"/>
      <import plugin="org.eclipse.osgi.services"/>
      <import plugin="org.apache.felix.scr"/>
      <import plugin="org.eclipse.equinox.util"/>
      <import plugin="org.w3c.css.sac"/>
      <import plugin="org.eclipse.emf.ecore.change"/>
      <import plugin="org.apache.batik.css"/>
      <import plugin="org.apache.batik.util"/>
      <import plugin="org.w3c.dom.events"/>
      <import plugin="org.w3c.dom.svg"/>
      <import plugin="javax.annotation"/>
      <import plugin="javax.inject"/>
      <import plugin="org.eclipse.e4.core.di.extensions"/>
      <import plugin="org.w3c.dom.smil"/>
      <import plugin="org.eclipse.equinox.p2.metadata.repository"/>
      <import plugin="org.eclipse.emf.edit"/>
      <import plugin="org.apache.commons.lang"/>
      <import plugin="org.eclipse.ltk.core.refactoring"/>
      <import plugin="org.eclipse.core.externaltools"/>
      <import plugin="org.eclipse.team.core"/>
      <import plugin="org.eclipse.jdt.core.manipulation"/>
      <import plugin="org.eclipse.ant.core"/>
      <import plugin="org.eclipse.ant.launching"/>
      <import plugin="org.eclipse.jdt.junit.core"/>
      <import plugin="org.eclipse.jdt.junit.runtime"/>
      <import plugin="org.eclipse.equinox.frameworkadmin"/>
      <import plugin="org.eclipse.equinox.simpleconfigurator.manipulator"/>
      <import plugin="org.eclipse.equinox.frameworkadmin.equinox"/>
      <import plugin="org.eclipse.equinox.simpleconfigurator"/>
      <import plugin="org.eclipse.xtext.generator"/>
      <import plugin="org.eclipse.xpand"/>
      <import plugin="org.eclipse.xtend"/>
      <import plugin="org.eclipse.emf.mwe.core"/>
      <import plugin="org.apache.commons.cli"/>
      <import plugin="org.eclipse.xtend.typesystem.emf"/>
      <import plugin="org.eclipse.emf.mwe.utils"/>
      <import plugin="org.eclipse.pde.launching"/>
      <import plugin="org.eclipse.pde.core"/>
      <import plugin="org.eclipse.pde.build"/>
      <import plugin="org.eclipse.update.configurator"/>
      <import plugin="org.eclipse.equinox.p2.director.app"/>
      <import plugin="org.eclipse.equinox.p2.director"/>
      <import plugin="org.eclipse.equinox.p2.operations"/>
      <import plugin="org.sat4j.core"/>
      <import plugin="org.sat4j.pb"/>
      <import plugin="org.eclipse.equinox.p2.jarprocessor"/>
      <import plugin="org.eclipse.equinox.p2.artifact.repository"/>
      <import plugin="org.eclipse.equinox.p2.publisher"/>
      <import plugin="org.eclipse.equinox.p2.publisher.eclipse"/>
      <import plugin="org.eclipse.equinox.p2.garbagecollector"/>
      <import plugin="org.eclipse.equinox.p2.repository.tools"/>
      <import plugin="org.eclipse.equinox.p2.touchpoint.eclipse"/>
      <import plugin="org.eclipse.jdt.junit4.runtime"/>
      <import plugin="org.eclipse.xpect"/>
      <import plugin="org.eclipse.ecf"/>
      <import plugin="org.eclipse.ecf.filetransfer"/>
      <import plugin="org.eclipse.ecf.provider.filetransfer"/>
      <import plugin="org.eclipse.ecf.identity"/>
      <import plugin="org.eclipse.jgit"/>
      <import plugin="javaewah"/>
      <import plugin="org.eclipse.equinox.launcher"/>
      <import plugin="ch.qos.logback.classic"/>
      <import plugin="org.eclipse.xsd.edit"/>
      <import plugin="org.eclipse.emf.ecore.edit"/>
      <import plugin="org.eclipse.xsd"/>
      <import plugin="org.eclipse.wst.common.project.facet.core"/>
      <import plugin="ch.qos.logback.core"/>
      <import plugin="org.eclipse.rse.subsystems.files.core"/>
      <import plugin="org.eclipse.rse.subsystems.files.local"/>
      <import plugin="org.eclipse.rse.core"/>
      <import plugin="org.eclipse.rse.services"/>
      <import plugin="org.eclipse.rse.services.local"/>
      <import plugin="org.eclipse.rse.connectorservice.local"/>
      <import plugin="org.eclipse.rse.subsystems.shells.core"/>
      <import plugin="org.eclipse.wst.html.core"/>
      <import plugin="org.eclipse.wst.css.core"/>
      <import plugin="org.eclipse.wst.server.core"/>
      <import plugin="org.eclipse.equinox.http.jetty"/>
      <import plugin="org.eclipse.equinox.http.registry"/>
      <import plugin="javax.servlet"/>
      <import plugin="org.eclipse.equinox.console"/>
      <import plugin="org.apache.felix.gogo.command"/>
      <import plugin="org.apache.felix.gogo.runtime"/>
      <import plugin="org.apache.felix.gogo.shell"/>
      <import plugin="org.eclipse.equinox.http.servlet"/>
      <import plugin="org.eclipse.jetty.continuation"/>
      <import plugin="org.eclipse.jetty.http"/>
      <import plugin="org.eclipse.jetty.io"/>
      <import plugin="org.eclipse.jetty.security"/>
      <import plugin="org.eclipse.jetty.server"/>
      <import plugin="org.eclipse.jetty.servlet"/>
      <import plugin="org.eclipse.jetty.util"/>
      <import plugin="com.fasterxml.jackson.core.jackson-annotations"/>
      <import plugin="com.fasterxml.jackson.core.jackson-core"/>
      <import plugin="com.fasterxml.jackson.core.jackson-databind"/>
      <import plugin="org.eclipse.lsp4j"/>
      <import plugin="org.eclipse.lsp4j.jsonrpc"/>
   </requires>

   <plugin
         id="org.eclipse.equinox.launcher.cocoa.macosx.x86_64"
         os="macosx"
         ws="cocoa"
         arch="x86_64"
         download-size="0"
         install-size="0"
         version="0.0.0"
         fragment="true"/>

   <plugin
         id="org.eclipse.equinox.launcher.win32.win32.x86_64"
         os="win32"
         ws="win32"
         arch="x86"
         download-size="0"
         install-size="0"
         version="0.0.0"
         fragment="true"/>

   <plugin
         id="org.eclipse.equinox.launcher.gtk.linux.x86_64"
         os="linux"
         ws="gtk"
         arch="x86"
         download-size="0"
         install-size="0"
         version="0.0.0"
         fragment="true"/>

</feature>
